halcyon/__init__.py
halcyon/__main__.py
halcyon/halcyon.py
halcyon/message.py
halcyon/restrunner.py
halcyon/room.py
halcyon_matrix-1.0.2.dist-info/LICENSE
halcyon_matrix-1.0.2.dist-info/METADATA
halcyon_matrix-1.0.2.dist-info/WHEEL
halcyon_matrix-1.0.2.dist-info/top_level.txt
halcyon_matrix-1.0.2.dist-info/RECORD
