Metadata-Version: 2.1
Name: halcyon-matrix
Version: 1.0.2
Summary: Halcyon is an easy to use matrix library
Home-page: https://github.com/WesR/Halcyon
Author: Wes Ring
Author-email: hello@wesring.com
License: UNKNOWN
Project-URL: Bug Tracker, https://github.com/WesR/Halcyon/issues
Platform: UNKNOWN
Classifier: Programming Language :: Python :: 3
Classifier: License :: OSI Approved :: BSD License
Classifier: Operating System :: OS Independent
Classifier: Topic :: Utilities
Classifier: Topic :: Software Development :: Libraries
Requires-Python: >=3.7
License-File: LICENSE
Requires-Dist: requests
